tls_occlusion/__init__.py
tls_occlusion/command_line.py
tls_occlusion/point_in_facets.py
tls_occlusion/parser/__init__.py
tls_occlusion/parser/hips.py
tls_occlusion/parser/material_map.py
tls_occlusion/parser/obj_parser.py
tls_occlusion/parser/parse_geometry.py
tls_occlusion/parser/parse_leaf.py
tls_occlusion/parser/shapes/__init__.py
tls_occlusion/utils/__init__.py
tls_occlusion/utils/bbox.py
tls_occlusion/utils/geometry.py
tls_occlusion/utils/point_cloud.py
tls_occlusion/utils/string.py
tls_occlusion-1.0.dist-info/DESCRIPTION.rst
tls_occlusion-1.0.dist-info/METADATA
tls_occlusion-1.0.dist-info/RECORD
tls_occlusion-1.0.dist-info/WHEEL
tls_occlusion-1.0.dist-info/entry_points.txt
tls_occlusion-1.0.dist-info/metadata.json
tls_occlusion-1.0.dist-info/top_level.txt
