Metadata-Version: 2.0
Name: tls-occlusion
Version: 1.0
Summary: Performs the matching of simulated point clouds to tree tree models in order to assess scanning occlusion.
Home-page: https://github.com/mattbv/tls_occlusion
Author: Matheus Boni Vicari
Author-email: matheus.boni.vicari@gmail.com
License: LICENSE.txt
Keywords: TLS occlusion point cloud LiDAR
Platform: UNKNOWN
Classifier: Programming Language :: Python
Classifier: Topic :: Scientific/Engineering
Requires-Dist: matplotlib (>=1.5.1)
Requires-Dist: numba (>=0.34.0)
Requires-Dist: numpy (>=1.11.3)
Requires-Dist: pandas (>=0.20.1)
Requires-Dist: scikit-image
Requires-Dist: scipy (>=0.19.0)
Requires-Dist: setuptools (>=36.0.1)
Requires-Dist: trimesh (>=2.14.17)
